{"cameraMode":{"drawMode":0,"name":"Shaded","section":"Shading Mode"},"sceneLighting":true,"audioPlay":false,"sceneViewState":{"showFog":true,"showMaterialUpdate":false,"showSkybox":true,"showFlares":true,"showImageEffects":true,"showParticleSystems":true,"showVisualEffectGraphs":true,"m_FxEnabled":true},"in2DMode":false,"pivot":{"x":-37.860923767089847,"y":-93.08670806884766,"z":52.57232666015625},"rotation":{"x":-0.28515487909317019,"y":0.2839426100254059,"z":-0.08886437118053436,"w":-0.9111363887786865},"size":254.17855834960938,"orthographic":false}